phishgambling/__init__.py
phishgambling/main.py
phishgambling-0.3.dist-info/METADATA
phishgambling-0.3.dist-info/WHEEL
phishgambling-0.3.dist-info/entry_points.txt
phishgambling-0.3.dist-info/top_level.txt
phishgambling-0.3.dist-info/RECORD
