Metadata-Version: 2.1
Name: phishgambling
Version: 0.3
Summary: This project is for film project only.
Author: Jan Leander
